decoratools/__init__.py
decoratools/capi/__init__.py
decoratools-0.0.19.dist-info/LICENSE
decoratools-0.0.19.dist-info/METADATA
decoratools-0.0.19.dist-info/WHEEL
decoratools-0.0.19.dist-info/top_level.txt
decoratools-0.0.19.dist-info/RECORD
