Metadata-Version: 2.1
Name: decoratools
Version: 0.0.19
Summary: Collection of useful decorators
Author-email: Quentin Bouget <ypsah@devyard.org>
License: MIT
Project-URL: homepage, https://gitlab.com/ypsah/decoratools
Project-URL: repository, https://gitlab.com/ypsah/decoratools
Keywords: decorator,utility,library
Classifier: Development Status :: 3 - Alpha
Classifier: Intended Audience :: Developers
Classifier: License :: OSI Approved :: MIT License
Classifier: Operating System :: OS Independent
Classifier: Programming Language :: Python
Classifier: Programming Language :: Python :: 3 :: Only
Classifier: Programming Language :: Python :: 3.11
Requires-Python: >=3.11
License-File: LICENSE
Requires-Dist: simple-git-versioning
